files/alu.sv
/*
Alu module for RISC-V 32-bit single-cycle processor.

base on alu decoder truth table from documentation.

outputs:
result : 32-bit result of the ALU operation
zero : 1-bit flag that is set to 1 if the result is zero, otherwise 0
*/
module alu (
    
    //inputs
    input logic [31:0] a, 
    input logic [31:0] b,
    input logic [3:0] ALUControl,

    //outputs
    output logic [31:0] y,
    output logic Zero,
    output logic Neg,

    output logic NegU
);
    //if ALUControl[0] is 1, we want to perform subtraction, which is equivalent to adding the
    // two's complement of b (i.e., ~b + 1 // the 1 is alucontrol[0])
    // if ALUControl[0] is 0, we want to perform addition, which is just a + b


    wire [31:0] b_eff   = b ^ {32{ALUControl[0]}};   // B or ~B
    wire        cin     = ALUControl[0];             // 0: ADD, 1: SUB

    // wide adders so we get carries
    wire [32:0] sum_agg  = {1'b0, a} + {1'b0, b_eff} + cin;     // full 32b add
    wire [31:0] sum     = sum_agg[31:0];
    wire        c_out   = sum_agg[32];

    // carry *into* MSB (from lower 31 bits) for signed overflow detection
    wire [31:0] low_sum31;
    wire        c_in31;
    assign {c_in31, low_sum31[30:0]} = {1'b0, a[30:0]} + {1'b0, b_eff[30:0]} + cin;

    // A control wire to check if we are in a subtraction/comparison path
    wire is_sub = ALUControl[0];        
    // Flags
    wire N = sum[31];
    wire V = c_in31 ^ c_out;     // signed overflow (add/sub)
    wire C = c_out;              // carry-out (for unsigned)

    assign Zero = (y == 32'b0);

    logic [4:0] shamt;
    assign shamt = b[4:0]; //logical shamt is rs2[4:0] or uimm = immediate[4:0] for shift instructions
    

    always_comb begin
        Neg =  1'b0;
        NegU = 1'b0;

        case (ALUControl)
            4'b0000: y = sum;                                  // add
            4'b0001: begin
                y = sum;                                  // SUB
                Neg = N^V;
                NegU = ~C;
            end 
            4'b0010: y = $unsigned(a) << shamt;                // slli ,sll

            4'b0011: begin  
                y = (N^V) ? 32'b1 : 32'b0;                         // slti , slt (using sub method as before)
              
            end
            4'b1011: begin 
                y = (~C) ? 32'b1 : 32'b0;                         // sltu, sltiu
            end                    
            4'b0100: y = a ^ b;                                 // xori .xor
            4'b0101: y = $unsigned(a) >> shamt;                 // srli, srl            
            4'b1101: y = $signed(a) >>> shamt;                  // srai, sra
            4'b0110: y = a | b;                                 // ori, or
            4'b0111: y = a & b;                                 // andi, and   

            default: y = 32'bxxxx_xxxx_xxxx_xxxx_xxxx_xxxx_xxxx_xxxx; // undefined
        endcase
    end
endmodule

tb/alu_tb.sv
`timescale 1ns/1ps

module alu_tb;
    // Signals
    logic clk;
    logic [31:0] a, b;
    logic [3:0]  ALUControl;
    logic [31:0] y;
    logic        Zero, Neg, NegU;

    // Error counter for tracking test status
    integer error_count = 0;

    // 1. Clock Generation
    always #5 clk = (clk === 1'b0); 

    // 2. DUT Instantiation
    alu dut (
        .a(a),
        .b(b),
        .ALUControl(ALUControl),
        .y(y),
        .Zero(Zero),
        .Neg(Neg),
        .NegU(NegU)
    );

    // 4. Combined Driver and Checker Task (Self-Checking)
    task verify(
        input [31:0] ta, 
        input [31:0] tb, 
        input [3:0]  top,
        input [31:0] exp_y,
        input        exp_zero,
        input        exp_neg,
        input        exp_negu
    );
        begin
            @(posedge clk);
            a          <= ta;
            b          <= tb;
            ALUControl <= top;
            
            @(posedge clk); // Wait for inputs to hit the DUT and evaluate
            #1;            // Small delay to allow combinational outputs to settle
            
            assert (y === exp_y && Zero === exp_zero && Neg === exp_neg && NegU === exp_negu)
                $display("SUCCESS | Time:%0t | OP:%b | A:%h B:%h | Y:%h | Flags [Z:%b N:%b NU:%b]",
                     $time, ALUControl, a, b, y, Zero, Neg, NegU);
            else begin
                $error("MISMATCH! OP:%b A:%h B:%h | Got: Y:%h Z:%b N:%b NU:%b | Expected: Y:%h Z:%b N:%b NU:%b",
                        ALUControl, a, b, y, Zero, Neg, NegU, exp_y, exp_zero, exp_neg, exp_negu);
                error_count = error_count + 1;
                
            end     
        end
    endtask

    // 5. Comprehensive Test Sequence (100% Instruction Matrix + Boundaries)
    initial begin
        // Initialize VCD dumping
        $dumpfile("tb_sim/alu_trace.vcd");
        $dumpvars(0, alu_tb);

        // Initialize signals
        clk = 0;
        a = 0; b = 0; ALUControl = 0;

        #10;
        $display("------- Starting End Cases Tests --------");

        // ==========================================
        // 1. ADD (4'b0000) Edge Cases
        // ==========================================
        $display("\n--- Testing ADD ---");
        // Zero baseline
        verify(32'h0000_0000, 32'h0000_0000, 4'b0000, 32'h0000_0000, 1, 0, 0);
        // Max negative addition (Your specific overflow case: INT_MIN + INT_MIN = 0)
        verify(32'h8000_0000, 32'h8000_0000, 4'b0000, 32'h0000_0000, 1, 0, 0);
        // Max positive addition (Signed overflow: INT_MAX + 1)
        verify(32'h7FFF_FFFF, 32'h0000_0001, 4'b0000, 32'h8000_0000, 0, 0, 0);
        // Unsigned roll-over (Carry out generated)
        verify(32'hFFFF_FFFF, 32'h0000_0001, 4'b0000, 32'h0000_0000, 1, 0, 0);

        // ==========================================
        // 2. SUB (4'b0001) Edge Cases
        // ==========================================
        $display("\n--- Testing SUB ---");
        // Equal numbers subtraction (Result 0)
        verify(32'hFFFF_FFFF, 32'hFFFF_FFFF, 4'b0001, 32'h0000_0000, 1, 0, 0);
        // Positive minus Negative causing signed overflow (7FFF_FFFF - (-1) = 8000_0000)
        verify(32'h7FFF_FFFF, 32'hFFFF_FFFF, 4'b0001, 32'h8000_0000, 0, 0, 1);
        // Small Unsigned minus Large Unsigned (Unsigned less-than / borrow check)
        verify(32'h0000_0005, 32'h0000_000A, 4'b0001, 32'hFFFF_FFFB, 0, 1, 1);

        // ==========================================
        // 3. SLL / SLLI (4'b0010) Shift Left Logical
        // ==========================================
        $display("\n--- Testing SLL ---");
        // Shift by 0
        verify(32'hFFFF_FFFF, 32'h0000_0000, 4'b0010, 32'hFFFF_FFFF, 0, 0, 0);
        // Shift by 1
        verify(32'h8000_0001, 32'h0000_0001, 4'b0010, 32'h0000_0002, 0, 0, 0);
        // Max Shift (31 bits)
        verify(32'hFFFF_FFFF, 32'h0000_001F, 4'b0010, 32'h8000_0000, 0, 0, 0);
        // another edge case
        verify(32'h1234_5678, 32'h0000_0020, 4'b0010, 32'h1234_5678, 0, 0, 0);

        // ==========================================
        // 4. SLT / SLTI (4'b0011) Set Less Than Signed
        // ==========================================
        $display("\n--- Testing SLT (Signed) ---");
        // Positive true condition
        verify(32'd10,        32'd20,        4'b0011, 32'h0000_0001, 0, 0, 0);
        // Negative true condition (-20 < -10)
        verify(32'hFFFF_FFEC, 32'hFFFF_FFF6, 4'b0011, 32'h0000_0001, 0, 0, 0);
        // False condition (positive vs negative)
        verify(32'd5,         32'hFFFF_FFFF, 4'b0011, 32'h0000_0000, 1, 0, 0);
        // Boundary Overflow Protection check (INT_MIN < 1 is True)
        verify(32'h8000_0000, 32'h0000_0001, 4'b0011, 32'h0000_0001, 0, 0, 0);

        // ==========================================
        // 5. SLTU / SLTIU (4'b1011) Set Less Than Unsigned
        // ==========================================
        $display("\n--- Testing SLTU (Unsigned) ---");
        // Small vs Large Unsigned (True)
        verify(32'h0000_0001, 32'hFFFF_FFFF, 4'b1011, 32'h0000_0001, 0, 0, 0);
        // Identical values (False)
        verify(32'hFFFF_FFFF, 32'hFFFF_FFFF, 4'b1011, 32'h0000_0000, 1, 0, 0);
        // Treat raw negative values as huge positive magnitudes (False)
        verify(32'hFFFF_FFFF, 32'h0000_0001, 4'b1011, 32'h0000_0000, 1, 0, 0);

        // ==========================================
        // 6. XOR / XORI (4'b0100)
        // ==========================================
        $display("\n--- Testing XOR ---");
        // Self XOR (Clears bits to 0)
        verify(32'hA5A5_5A5A, 32'hA5A5_5A5A, 4'b0100, 32'h0000_0000, 1, 0, 0);
        // Complementary XOR (Sets bits to 1)
        verify(32'h5555_5555, 32'hAAAA_AAAA, 4'b0100, 32'hFFFF_FFFF, 0, 0, 0);

        // ==========================================
        // 7. SRL / SRLI (4'b0101) Logical Right Shift
        // ==========================================
        $display("\n--- Testing SRL ---");
        // Shift right by 1 (Should shift a 0 into MSB)
        verify(32'h8000_0000, 32'h0000_0001, 4'b0101, 32'h4000_0000, 0, 0, 0);
        // Shift right by 31
        verify(32'h8000_0000, 32'h0000_001F, 4'b0101, 32'h0000_0001, 0, 0, 0);

        // ==========================================
        // 8. SRA / SRAI (4'b1101) Arithmetic Right Shift
        // ==========================================
        $display("\n--- Testing SRA ---");
        // Shift right on a negative number (Should preserve/replicate sign bit)
        verify(32'h8000_0000, 32'h0000_0001, 4'b1101, 32'hC000_0000, 0, 0, 0);
        // Shift right on a positive number (Should preserve 0 in MSB)
        verify(32'h7000_0000, 32'h0000_0001, 4'b1101, 32'h3800_0000, 0, 0, 0);
        // Full arithmetic extension down to 31 shifts
        verify(32'h8000_0000, 32'h0000_001F, 4'b1101, 32'hFFFF_FFFF, 0, 0, 0);

        // ==========================================
        // 9. OR / ORI (4'b0110)
        // ==========================================
        $display("\n--- Testing OR ---");
        verify(32'hF0F0_0000, 32'h0000_0F0F, 4'b0110, 32'hF0F0_0F0F, 0, 0, 0);

        // ==========================================
        // 10. AND / ANDI (4'b0111)
        // ==========================================
        $display("\n--- Testing AND ---");
        verify(32'hFFFF_0000, 32'hF0F0_FFFF, 4'b0111, 32'hF0F0_0000, 0, 0, 0);

        // Final Reporting
        #20;
        $display("\n------- Verification Finished -------");
        if (error_count == 0) begin
            $display(">>>> SUCCESS: 100%% Instruction Coverage Completed with 0 Errors! <<<<");
        end else begin
            $display(">>>> FAILURE: Verification complete with %d mismatches listed above. <<<<", error_count);
        end
       
        $finish;
    end

endmodule

tb_sim/alu_trace.vcd
$date
	Tue May 26 12:16:59 2026
$end
$version
	Icarus Verilog
$end
$timescale
	1ps
$end
$scope module alu_tb $end
$var wire 32 ! y [31:0] $end
$var wire 1 " Zero $end
$var wire 1 # NegU $end
$var wire 1 $ Neg $end
$var reg 4 % ALUControl [3:0] $end
$var reg 32 & a [31:0] $end
$var reg 32 ' b [31:0] $end
$var reg 1 ( clk $end
$var integer 32 ) error_count [31:0] $end
$scope module dut $end
$var wire 4 * ALUControl [3:0] $end
$var wire 1 + C $end
$var wire 1 , V $end
$var wire 32 - a [31:0] $end
$var wire 32 . b [31:0] $end
$var wire 32 / b_eff [31:0] $end
$var wire 33 0 sum_agg [32:0] $end
$var wire 32 1 sum [31:0] $end
$var wire 5 2 shamt [4:0] $end
$var wire 32 3 low_sum31 [31:0] $end
$var wire 1 4 is_sub $end
$var wire 1 5 cin $end
$var wire 1 6 c_out $end
$var wire 1 7 c_in31 $end
$var wire 1 " Zero $end
$var wire 1 8 N $end
$var reg 1 $ Neg $end
$var reg 1 # NegU $end
$var reg 32 9 y [31:0] $end
$upscope $end
$scope task verify $end
$var reg 1 : exp_neg $end
$var reg 1 ; exp_negu $end
$var reg 32 < exp_y [31:0] $end
$var reg 1 = exp_zero $end
$var reg 32 > ta [31:0] $end
$var reg 32 ? tb [31:0] $end
$var reg 4 @ top [3:0] $end
$upscope $end
$upscope $end
$enddefinitions $end
$comment Show the parameter values. $end
$dumpall
$end
#0
$dumpvars
bx @
bx ?
bx >
x=
bx <
x;
x:
b0 9
08
07
06
05
04
bz0000000000000000000000000000000 3
b0 2
b0 1
b0 0
b0 /
b0 .
b0 -
0,
0+
b0 *
b0 )
0(
b0 '
b0 &
b0 %
0$
0#
1"
b0 !
$end
#5000
1(
#10000
0(
0;
0:
1=
b0 <
b0 @
b0 ?
b0 >
#15000
1(
#20000
0(
#25000
1(
#26000
b10000000000000000000000000000000 ?
b10000000000000000000000000000000 >
#30000
0(
#35000
1,
1+
16
08
b10000000000000000000000000000000 /
1"
b0 !
b0 9
b0 1
b10000000000000000000000000000000 '
b10000000000000000000000000000000 .
b100000000000000000000000000000000 0
b10000000000000000000000000000000 &
b10000000000000000000000000000000 -
1(
#40000
0(
#45000
1(
#46000
0=
b10000000000000000000000000000000 <
b1 ?
b1111111111111111111111111111111 >
#50000
0(
#55000
17
18
1,
bz0000000000000000000000000000000 3
b1 /
b1 2
0"
b10000000000000000000000000000000 !
b10000000000000000000000000000000 9
b10000000000000000000000000000000 1
0+
06
b1 '
b1 .
b10000000000000000000000000000000 0
b1111111111111111111111111111111 &
b1111111111111111111111111111111 -
1(
#60000
0(
#65000
1(
#66000
1=
b0 <
b11111111111111111111111111111111 >
#70000
0(
#75000
08
0,
1"
b0 !
b0 9
b0 1
1+
16
b100000000000000000000000000000000 0
b11111111111111111111111111111111 &
b11111111111111111111111111111111 -
1(
#80000
0(
#85000
1(
#86000
b1 @
b11111111111111111111111111111111 ?
#90000
0(
#95000
0$
08
1"
b0 !
b0 9
bz0000000000000000000000000000000 3
b0 1
15
14
b100000000000000000000000000000000 0
b0 /
b11111 2
b1 %
b1 *
b11111111111111111111111111111111 '
b11111111111111111111111111111111 .
1(
#100000
0(
#105000
1(
#106000
1;
0=
b10000000000000000000000000000000 <
b1111111111111111111111111111111 >
#110000
0(
#115000
18
1,
1#
0"
b10000000000000000000000000000000 !
b10000000000000000000000000000000 9
b10000000000000000000000000000000 1
0+
06
b10000000000000000000000000000000 0
b1111111111111111111111111111111 &
b1111111111111111111111111111111 -
1(
#120000
0(
#125000
1(
#126000
1:
b11111111111111111111111111111011 <
b1010 ?
b101 >
#130000
0(
#135000
0,
1$
18
bz1111111111111111111111111111011 3
07
b11111111111111111111111111110101 /
b1010 2
b11111111111111111111111111111011 !
b11111111111111111111111111111011 9
1#
b11111111111111111111111111111011 1
b1010 '
b1010 .
b11111111111111111111111111111011 0
b101 &
b101 -
1(
#140000
0(
#145000
1(
#146000
0;
0:
b11111111111111111111111111111111 <
b10 @
b0 ?
b11111111111111111111111111111111 >
#150000
0(
#155000
bz1111111111111111111111111111111 3
07
05
04
b0 /
b0 2
b11111111111111111111111111111111 !
b11111111111111111111111111111111 9
0#
0$
b11111111111111111111111111111111 1
0+
06
b10 %
b10 *
b0 '
b0 .
b11111111111111111111111111111111 0
b11111111111111111111111111111111 &
b11111111111111111111111111111111 -
1(
#160000
0(
#165000
1(
#166000
b10 <
b1 ?
b10000000000000000000000000000001 >
#170000
0(
#175000
bz0000000000000000000000000000010 3
b1 /
b1 2
b10 !
b10 9
b10000000000000000000000000000010 1
b1 '
b1 .
b10000000000000000000000000000010 0
b10000000000000000000000000000001 &
b10000000000000000000000000000001 -
1(
#180000
0(
#185000
1(
#186000
b10000000000000000000000000000000 <
b11111 ?
b11111111111111111111111111111111 >
#190000
0(
#195000
08
bz0000000000000000000000000011110 3
17
b11111 /
b11111 2
b10000000000000000000000000000000 !
b10000000000000000000000000000000 9
b11110 1
1+
16
b11111 '
b11111 .
b100000000000000000000000000011110 0
b11111111111111111111111111111111 &
b11111111111111111111111111111111 -
1(
#200000
0(
#205000
1(
#206000
b10010001101000101011001111000 <
b100000 ?
b10010001101000101011001111000 >
#210000
0(
#215000
bz0010010001101000101011010011000 3
07
b100000 /
b0 2
0"
b10010001101000101011001111000 !
b10010001101000101011001111000 9
b10010001101000101011010011000 1
0+
06
b100000 '
b100000 .
b10010001101000101011010011000 0
b10010001101000101011001111000 &
b10010001101000101011001111000 -
1(
#220000
0(
#225000
1(
#226000
b1 <
b11 @
b10100 ?
b1010 >
#230000
0(
#235000
18
bz1111111111111111111111111110110 3
15
14
b11111111111111111111111111101011 /
b10100 2
0"
b1 !
b1 9
b11111111111111111111111111110110 1
b11 %
b11 *
b10100 '
b10100 .
b11111111111111111111111111110110 0
b1010 &
b1010 -
1(
#240000
0(
#245000
1(
#246000
b11111111111111111111111111110110 ?
b11111111111111111111111111101100 >
#250000
0(
#255000
bz1111111111111111111111111110110 3
07
b1001 /
b10110 2
b11111111111111111111111111110110 1
0+
06
b11111111111111111111111111110110 '
b11111111111111111111111111110110 .
b11111111111111111111111111110110 0
b11111111111111111111111111101100 &
b11111111111111111111111111101100 -
1(
#260000
0(
#265000
1(
#266000
1=
b0 <
b11111111111111111111111111111111 ?
b101 >
#270000
0(
#275000
1"
b0 !
b0 9
08
bz0000000000000000000000000000110 3
b0 /
b11111 2
b110 1
b11111111111111111111111111111111 '
b11111111111111111111111111111111 .
b110 0
b101 &
b101 -
1(
#280000
0(
#285000
1(
#286000
0=
b1 <
b1 ?
b10000000000000000000000000000000 >
#290000
0(
#295000
1,
1+
16
0"
b1 !
b1 9
08
bz1111111111111111111111111111111 3
b11111111111111111111111111111110 /
b1 2
b1111111111111111111111111111111 1
b1 '
b1 .
b101111111111111111111111111111111 0
b10000000000000000000000000000000 &
b10000000000000000000000000000000 -
1(
#300000
0(
#305000
1(
#306000
b1011 @
b11111111111111111111111111111111 ?
b1 >
#310000
0(
#315000
0,
0+
06
bz0000000000000000000000000000010 3
07
b0 /
b11111 2
0"
b1 !
b1 9
b10 1
b1011 %
b1011 *
b11111111111111111111111111111111 '
b11111111111111111111111111111111 .
b10 0
b1 &
b1 -
1(
#320000
0(
#325000
1(
#326000
1=
b0 <
b11111111111111111111111111111111 >
#330000
0(
#335000
bz0000000000000000000000000000000 3
17
1"
b0 !
b0 9
b0 1
1+
16
b100000000000000000000000000000000 0
b11111111111111111111111111111111 &
b11111111111111111111111111111111 -
1(
#340000
0(
#345000
1(
#346000
b1 ?
#350000
0(
#355000
18
bz1111111111111111111111111111110 3
b11111111111111111111111111111110 1
b111111111111111111111111111111110 0
b11111111111111111111111111111110 /
b1 2
b1 '
b1 .
1(
#360000
0(
#365000
1(
#366000
b100 @
b10100101101001010101101001011010 ?
b10100101101001010101101001011010 >
#370000
0(
#375000
08
1,
07
1+
16
bz1001011010010101011010010110100 3
05
04
b10100101101001010101101001011010 /
b11010 2
b1001011010010101011010010110100 1
b100 %
b100 *
b10100101101001010101101001011010 '
b10100101101001010101101001011010 .
b101001011010010101011010010110100 0
b10100101101001010101101001011010 &
b10100101101001010101101001011010 -
1(
#380000
0(
#385000
1(
#386000
0=
b11111111111111111111111111111111 <
b10101010101010101010101010101010 ?
b1010101010101010101010101010101 >
#390000
0(
#395000
18
0,
bz1111111111111111111111111111111 3
b10101010101010101010101010101010 /
b1010 2
0"
b11111111111111111111111111111111 !
b11111111111111111111111111111111 9
b11111111111111111111111111111111 1
0+
06
b10101010101010101010101010101010 '
b10101010101010101010101010101010 .
b11111111111111111111111111111111 0
b1010101010101010101010101010101 &
b1010101010101010101010101010101 -
1(
#400000
0(
#405000
1(
#406000
b1000000000000000000000000000000 <
b101 @
b1 ?
b10000000000000000000000000000000 >
#410000
0(
#415000
08
1,
bz1111111111111111111111111111111 3
15
14
b11111111111111111111111111111110 /
b1 2
b1000000000000000000000000000000 !
b1000000000000000000000000000000 9
b1111111111111111111111111111111 1
1+
16
b101 %
b101 *
b1 '
b1 .
b101111111111111111111111111111111 0
b10000000000000000000000000000000 &
b10000000000000000000000000000000 -
1(
#420000
0(
#425000
1(
#426000
b1 <
b11111 ?
#430000
0(
#435000
bz1111111111111111111111111100001 3
b1111111111111111111111111100001 1
b101111111111111111111111111100001 0
b11111111111111111111111111100000 /
b1 !
b1 9
b11111 2
b11111 '
b11111 .
1(
#440000
0(
#445000
1(
#446000
b11000000000000000000000000000000 <
b1101 @
b1 ?
#450000
0(
#455000
bz1111111111111111111111111111111 3
b1111111111111111111111111111111 1
b101111111111111111111111111111111 0
b11111111111111111111111111111110 /
b11000000000000000000000000000000 !
b11000000000000000000000000000000 9
b1 2
b1101 %
b1101 *
b1 '
b1 .
1(
#460000
0(
#465000
1(
#466000
b111000000000000000000000000000 <
b1110000000000000000000000000000 >
#470000
0(
#475000
0,
bz1101111111111111111111111111111 3
17
b111000000000000000000000000000 !
b111000000000000000000000000000 9
b1101111111111111111111111111111 1
b101101111111111111111111111111111 0
b1110000000000000000000000000000 &
b1110000000000000000000000000000 -
1(
#480000
0(
#485000
1(
#486000
b11111111111111111111111111111111 <
b11111 ?
b10000000000000000000000000000000 >
#490000
0(
#495000
1,
bz1111111111111111111111111100001 3
07
b11111111111111111111111111100000 /
b11111 2
b11111111111111111111111111111111 !
b11111111111111111111111111111111 9
b1111111111111111111111111100001 1
b11111 '
b11111 .
b101111111111111111111111111100001 0
b10000000000000000000000000000000 &
b10000000000000000000000000000000 -
1(
#500000
0(
#505000
1(
#506000
b11110000111100000000111100001111 <
b110 @
b111100001111 ?
b11110000111100000000000000000000 >
#510000
0(
#515000
0+
06
0,
18
bz1110000111100000000111100001111 3
07
05
04
b111100001111 /
b1111 2
b11110000111100000000111100001111 !
b11110000111100000000111100001111 9
b11110000111100000000111100001111 1
b110 %
b110 *
b111100001111 '
b111100001111 .
b11110000111100000000111100001111 0
b11110000111100000000000000000000 &
b11110000111100000000000000000000 -
1(
#520000
0(
#525000
1(
#526000
b11110000111100000000000000000000 <
b111 @
b11110000111100001111111111111111 ?
b11111111111111110000000000000000 >
#530000
0(
#535000
08
17
1+
16
bz0001111000011100000000000000001 3
15
14
b1111000011110000000000000000 /
b11111 2
b11110000111100000000000000000000 !
b11110000111100000000000000000000 9
b1111000011100000000000000001 1
b111 %
b111 *
b11110000111100001111111111111111 '
b11110000111100001111111111111111 .
b100001111000011100000000000000001 0
b11111111111111110000000000000000 &
b11111111111111110000000000000000 -
1(
