files/branchLogic.sv
module branchLogic(
    input logic [2:0] funct3,
    input logic Zero,
    input logic Neg,
    input logic NegU,
    output logic btFlag
);

wire funct3_lsb = funct3[0];
always_comb begin
    case(funct3)
        3'b000:  btFlag = Zero ;    // beq     
        3'b001:  btFlag = ~Zero ;   // bne
        3'b100:  btFlag = Neg  ;    // blt
        3'b101:  btFlag = ~Neg  ;   // bge
        3'b110:  btFlag = NegU  ;   // bltu
        3'b111:  btFlag = ~NegU ;   // bgeu
        default:
         btFlag = 1'bx;
    endcase
end
endmodule

tb/bl_tb.sv
`timescale 1ns / 1ps

module bl_tb;

    // Testbench signals
    logic [2:0] funct3;
    logic       Zero;
    logic       Neg;
    logic       NegU;
    wire        btFlag;

    // Simulation control
    logic clk;
    integer error_count = 0;


    always #5 clk = (clk === 1'b0); 

    // Instantiate the Device Under Test (DUT)
    branchLogic dut (
        .funct3(funct3),
        .Zero(Zero),
        .Neg(Neg),
        .NegU(NegU),
        .btFlag(btFlag)
    );

    // Verification Task
    task verify(
        input [2:0] t_funct3,
        input       t_Zero,
        input       t_Neg,
        input       t_NegU,
        input        exp_btFlag
    );
        begin
            @(posedge clk);
            funct3 <= t_funct3;
            Zero   <= t_Zero;
            Neg    <= t_Neg;
            NegU   <= t_NegU;
            
            @(posedge clk);
            #1; // Allow combinational logic to settle completely
            
            assert (btFlag === exp_btFlag) begin
                $display("SUCCESS | Time:%0t | funct3:%b | Flags [Z:%b N:%b NU:%b] | Target btFlag:%b", 
                         $time, funct3, Zero, Neg, NegU, btFlag);
            end else begin
                $error("MISMATCH! funct3:%b Flags [Z:%b N:%b NU:%b] | Got btFlag:%b | Expected:%b",
                       funct3, Zero, Neg, NegU, btFlag, exp_btFlag);
                error_count = error_count + 1;
            end
        end
    endtask

    // Main Test Vector Execution
    initial begin
          // Initialize VCD dumping
        $dumpfile("tb_sim/bl_trace.vcd");
        $dumpvars(0, bl_tb);
        // Initialize inputs
        clk = 0;
        funct3 = 3'b000;
        Zero = 0;
        Neg = 0;
        NegU = 0;

        $display("--- Starting Branch Logic Tests ---");
        #10;

        // ==========================================
        // 1. BEQ (3'b000) - Branch if Equal (Zero == 1)
        // ==========================================
        $display("\n--- Testing BEQ ---");
        verify(3'b000, 1, 0, 0, 1); // True
        verify(3'b000, 0, 1, 1, 0); // False (other flags ignored)

        // ==========================================
        // 2. BNE (3'b001) - Branch if Not Equal (Zero == 0)
        // ==========================================
        $display("\n--- Testing BNE ---");
        verify(3'b001, 0, 0, 0, 1); // True
        verify(3'b001, 1, 1, 1, 0); // False

        // ==========================================
        // 3. BLT (3'b100) - Branch if Less Than
        $display("\n--- Testing BLT ---");
        verify(3'b100, 0, 1, 0, 1); // True
        verify(3'b100, 1, 0, 1, 0); // False

        // ==========================================
        // 4. BGE (3'b101) - Branch if Greater or Equal Signed (Neg == 0)
        // ==========================================
        $display("\n--- Testing BGE ---");
        verify(3'b101, 0, 0, 1, 1); // True
        verify(3'b101, 0, 1, 0, 0); // False

        // ==========================================
        // 5. BLTU (3'b110) - Branch if Less Than Unsigned (NegU == 1)
        // ==========================================
        $display("\n--- Testing BLTU ---");
        verify(3'b110, 0, 0, 1, 1); // True
        verify(3'b110, 1, 1, 0, 0); // False

        // ==========================================
        // 6. BGEU (3'b111) - Branch if Greater or Equal Unsigned (NegU == 0)
        // ==========================================
        $display("\n--- Testing BGEU ---");
        verify(3'b111, 0, 1, 0, 1); // True
        verify(3'b111, 0, 0, 1, 0); // False

        // Summary Results
        $display("\n==========================================");
        if (error_count == 0) begin
            $display("  ALL TESTS PASSED SUCCESSFULLY! (Errors: 0)");
        end else begin
            $display("  TESTBENCH FAILED with %0d errors.", error_count);
        end
        $display("==========================================");

        $finish;
    end

endmodule

tb_sim/bl_trace.vcd
$date
	Sun May 24 22:34:28 2026
$end
$version
	Icarus Verilog
$end
$timescale
	1ps
$end
$scope module bl_tb $end
$var wire 1 ! btFlag $end
$var reg 1 " Neg $end
$var reg 1 # NegU $end
$var reg 1 $ Zero $end
$var reg 1 % clk $end
$var reg 3 & funct3 [2:0] $end
$var integer 32 ' error_count [31:0] $end
$scope module dut $end
$var wire 1 " Neg $end
$var wire 1 # NegU $end
$var wire 1 $ Zero $end
$var wire 3 ( funct3 [2:0] $end
$var wire 1 ) funct3_lsb $end
$var reg 1 ! btFlag $end
$upscope $end
$scope task verify $end
$var reg 1 * exp_btFlag $end
$var reg 1 + t_Neg $end
$var reg 1 , t_NegU $end
$var reg 1 - t_Zero $end
$var reg 3 . t_funct3 [2:0] $end
$upscope $end
$upscope $end
$enddefinitions $end
$comment Show the parameter values. $end
$dumpall
$end
#0
$dumpvars
bx .
x-
x,
x+
x*
0)
b0 (
b0 '
b0 &
0%
0$
0#
0"
0!
$end
#5000
1%
#10000
0%
1*
0,
0+
1-
b0 .
#15000
1!
1$
1%
#20000
0%
#25000
1%
#26000
0*
1,
1+
0-
#30000
0%
#35000
0!
1#
1"
0$
1%
#40000
0%
#45000
1%
#46000
1*
0,
0+
b1 .
#50000
0%
#55000
1!
1)
0#
0"
b1 &
b1 (
1%
#60000
0%
#65000
1%
#66000
0*
1,
1+
1-
#70000
0%
#75000
0!
1#
1"
1$
1%
#80000
0%
#85000
1%
#86000
1*
0,
0-
b100 .
#90000
0%
#95000
1!
0)
0#
0$
b100 &
b100 (
1%
#100000
0%
#105000
1%
#106000
0*
1,
0+
1-
#110000
0%
#115000
0!
1#
0"
1$
1%
#120000
0%
#125000
1%
#126000
1*
0-
b101 .
#130000
0%
#135000
1!
1)
0$
b101 &
b101 (
1%
#140000
0%
#145000
1%
#146000
0*
0,
1+
#150000
0%
#155000
0!
0#
1"
1%
#160000
0%
#165000
1%
#166000
1*
1,
0+
b110 .
#170000
0%
#175000
1!
0)
1#
0"
b110 &
b110 (
1%
#180000
0%
#185000
1%
#186000
0*
0,
1+
1-
#190000
0%
#195000
0!
0#
1"
1$
1%
#200000
0%
#205000
1%
#206000
1*
0-
b111 .
#210000
0%
#215000
1!
1)
0$
b111 &
b111 (
1%
#220000
0%
#225000
1%
#226000
0*
1,
0+
#230000
0%
#235000
0!
1#
0"
1%
