files/registerFile.sv
/*
Register file module for a simple CPU design. 
This module contains 32 registers, each 32 bits wide. 
It supports reading from two source registers and writing to a destination register on the rising edge of the clock.
 The register at index 0 is hardwired to zero and cannot be modified.
 

*/
module registerFile (
    input clk,
    input logic we3,             // Write enable
    input logic [4:0] a1,a2,    // Read  adresss
    input logic [4:0] a3,      // Write address
    input logic [31:0] wd3,     // Write data
    output logic [31:0] rd1,rd2   // Read data

);
    // Register array : 32 registers of 32 bits each: x0 is index 0
    logic [31:0] rf [31:0];

    // Synchronous Write: Register x0 is protected from writes
    always_ff @(posedge clk) begin
        if(we3 && (a3 != 0))
            rf[a3] <= wd3;
    end
        
    // Asynchronous Reads: Register x0 always returns 0
    assign rd1 = a1!= 0 ? rf[a1] : 0;
    assign rd2 = a2!= 0 ? rf[a2] : 0;

    
endmodule

tb/rf_tb.sv
`timescale 1ns/1ps

module rf_tb;
    // Signals
    logic        clk;
    logic        we3;
    logic [4:0]  a1, a2, a3;
    logic [31:0] wd3;
    logic [31:0] rd1, rd2;

    // Error counter for tracking test status
    integer error_count = 0;

    // Golden Model Mirror for Tracking Expected States in Random Testing
    // (An array of 32 elements, 32-bits wide)
    logic [31:0] golden_rf [31:0];
    integer i;

    // 1. Clock Generation
    always #5 clk = (clk === 1'b0); 

    // 2. DUT Instantiation
    registerFile dut (
        .clk(clk),
        .we3(we3),
        .a1(a1),
        .a2(a2),
        .a3(a3),
        .wd3(wd3),
        .rd1(rd1),
        .rd2(rd2)
    );

    // 4. Combined Driver and Checker Task (Self-Checking)
    task verify_write_read(
        input        t_we3,
        input [4:0]  t_a3,
        input [31:0] t_wd3,
        input [4:0]  t_a1,
        input [4:0]  t_a2,
        input [31:0] exp_rd1,
        input [31:0] exp_rd2
    );
        begin
            @(posedge clk);
            we3 <= t_we3;
            a3  <= t_a3;
            wd3 <= t_wd3;
            a1  <= t_a1;
            a2  <= t_a2;

          
            #1;            // Small delay to let asynchronous outputs settle
            
            assert (rd1 === exp_rd1 && rd2 === exp_rd2) begin
                // Silent on success during large loops to keep logs clean
            end else begin
                $error("MISMATCH! WE:%b A3:%d WD:%h | A1:%d Got RD1:%h (Exp:%h) | A2:%d Got RD2:%h (Exp:%h)",
                        we3, a3, wd3, a1, rd1, exp_rd1, a2, rd2, exp_rd2);
                error_count = error_count + 1;
            end     
            @(posedge clk);
        end
    endtask

    // 5. Test Sequence
    initial begin
        // Initialize VCD dumping
        $dumpfile("tb_sim/rf.vcd");
        $dumpvars(0, rf_tb);

        // Initialize signals & Golden Model
        clk = 0;
        we3 = 0; a1 = 0; a2 = 0; a3 = 0; wd3 = 0;
        for (i = 0; i < 32; i = i + 1) begin
            dut.rf[i]= 32'h0; 
            golden_rf[i] = 32'h0; // Assume registers clear to 0 internally or contain 0 for tracking
        end

        #10;
        $display("------- Starting Register File Directed Tests --------");

        // Directed Edge Cases (From previous stable version)
        verify_write_read(0, 5'd0, 32'h0, 5'd0, 5'd0, 32'h0, 32'h0); // Reset baseline
        verify_write_read(1, 5'd0, 32'hFFFF_FFFF, 5'd0, 5'd0, 32'h0, 32'h0); // x0 Protection

        // ==========================================================
        // 6. Constraint-Randomized Verification Loop (Icarus Friendly)
        // ==========================================================
        $display("\n--- Starting 200 Iterations of Random Testing ---");
        
        for (i = 0; i < 200; i = i + 1) begin
            // 1. Constrained generation using $urandom variables
            logic        rand_we3;
            logic [4:0]  rand_a3;
            logic [31:0] rand_wd3;
            logic [4:0]  rand_a1;
            logic [4:0]  rand_a2;
            
            logic [31:0] next_exp_rd1;
            logic [31:0] next_exp_rd2;

            // Roll the dice for inputs
            rand_we3 = $urandom_range(0, 1);       // 50% chance to write
            rand_a3  = $urandom_range(0, 31);      // Random destination address (0 to 31)
            rand_wd3 = $urandom();                 // Completely random 32-bit data
            rand_a1  = $urandom_range(0, 31);      // Random read register 1
            rand_a2  = $urandom_range(0, 31);      // Random read register 2

            // 2. Pre-calculate expected outputs using our Golden Model *before* the clock ticks
            next_exp_rd1 = (rand_a1 == 5'd0) ? 32'h0 : golden_rf[rand_a1];
            next_exp_rd2 = (rand_a2 == 5'd0) ? 32'h0 : golden_rf[rand_a2];

            // 3. Update our internal Golden Model to predict what the DUT will do on this clock cycle
            if (rand_we3 && (rand_a3 != 5'd0)) begin
                golden_rf[rand_a3] = rand_wd3;
            end

            // 4. Send the random stimuli to the verification task
            verify_write_read(rand_we3, rand_a3, rand_wd3, rand_a1, rand_a2, next_exp_rd1, next_exp_rd2);
        end

        // Final Reporting
        #20;
        $display("\n------- Verification Finished -------");
        if (error_count == 0) begin
            $display(">>>> SUCCESS: Directed + 200 Random Test Cycles Passed with 0 Errors! <<<<");
        end else begin
            $display(">>>> FAILURE: Verification complete with %d mismatches. <<<<", error_count);
        end
       
        $finish;
    end

endmodule

tb_sim/rf.vcd
$date
	Tue May 26 14:28:17 2026
$end
$version
	Icarus Verilog
$end
$timescale
	1ps
$end
$scope module rf_tb $end
$var wire 32 ! rd2 [31:0] $end
$var wire 32 " rd1 [31:0] $end
$var reg 5 # a1 [4:0] $end
$var reg 5 $ a2 [4:0] $end
$var reg 5 % a3 [4:0] $end
$var reg 1 & clk $end
$var reg 32 ' wd3 [31:0] $end
$var reg 1 ( we3 $end
$var integer 32 ) error_count [31:0] $end
$var integer 32 * i [31:0] $end
$scope module dut $end
$var wire 5 + a1 [4:0] $end
$var wire 5 , a2 [4:0] $end
$var wire 5 - a3 [4:0] $end
$var wire 1 & clk $end
$var wire 32 . wd3 [31:0] $end
$var wire 1 ( we3 $end
$var wire 32 / rd2 [31:0] $end
$var wire 32 0 rd1 [31:0] $end
$upscope $end
$scope begin $unm_blk_7 $end
$var reg 32 1 next_exp_rd1 [31:0] $end
$var reg 32 2 next_exp_rd2 [31:0] $end
$var reg 5 3 rand_a1 [4:0] $end
$var reg 5 4 rand_a2 [4:0] $end
$var reg 5 5 rand_a3 [4:0] $end
$var reg 32 6 rand_wd3 [31:0] $end
$var reg 1 7 rand_we3 $end
$upscope $end
$scope task verify_write_read $end
$var reg 32 8 exp_rd1 [31:0] $end
$var reg 32 9 exp_rd2 [31:0] $end
$var reg 5 : t_a1 [4:0] $end
$var reg 5 ; t_a2 [4:0] $end
$var reg 5 < t_a3 [4:0] $end
$var reg 32 = t_wd3 [31:0] $end
$var reg 1 > t_we3 $end
$upscope $end
$upscope $end
$enddefinitions $end
$comment Show the parameter values. $end
$dumpall
$end
#0
$dumpvars
x>
bx =
bx <
bx ;
bx :
bx 9
bx 8
x7
bx 6
bx 5
bx 4
bx 3
bx 2
bx 1
b0 0
b0 /
b0 .
b0 -
b0 ,
b0 +
b100000 *
b0 )
0(
b0 '
0&
b0 %
b0 $
b0 #
b0 "
b0 !
$end
#5000
1&
#10000
0&
b0 9
b0 8
b0 ;
b0 :
b0 =
b0 <
0>
#15000
1&
#20000
0&
#25000
b11111111111111111111111111111111 =
1>
1&
#30000
0&
#35000
b11111111111111111111111111111111 '
b11111111111111111111111111111111 .
1(
1&
#40000
0&
#45000
b10000 ;
b110 :
b100100001001101011000001001 =
b1000 <
b0 2
b0 1
b10000 4
b110 3
b100100001001101011000001001 6
b1000 5
17
b0 *
1&
#50000
0&
#55000
b10000 $
b10000 ,
b110 #
b110 +
b100100001001101011000001001 '
b100100001001101011000001001 .
b1000 %
b1000 -
1&
#60000
0&
#65000
b10000 :
b1001001101110101001000010010 =
b110 <
b10000 3
b1001001101110101001000010010 6
b110 5
b1 *
1&
#70000
0&
#75000
b10000 #
b10000 +
b1001001101110101001000010010 '
b1001001101110101001000010010 .
b110 %
b110 -
1&
#80000
0&
#85000
b11111 ;
b11000 :
b11110110110101000101011111101101 =
b10011 <
b11111 4
b11000 3
b11110110110101000101011111101101 6
b10011 5
b10 *
1&
#90000
0&
#95000
b11111 $
b11111 ,
b11000 #
b11000 +
b11110110110101000101011111101101 '
b11110110110101000101011111101101 .
b10011 %
b10011 -
1&
#100000
0&
#105000
b111 ;
b11110 :
b1010101000100111101001010101010 =
b1100 <
0>
b111 4
b11110 3
b1010101000100111101001010101010 6
b1100 5
07
b11 *
1&
#110000
0&
#115000
b111 $
b111 ,
b11110 #
b11110 +
b1010101000100111101001010101010 '
b1010101000100111101001010101010 .
b1100 %
b1100 -
0(
1&
#120000
0&
#125000
b1110 ;
b1100 :
b11111001001100000110100111110010 =
b11000 <
b1110 4
b1100 3
b11111001001100000110100111110010 6
b11000 5
b100 *
1&
#130000
0&
#135000
b1110 $
b1110 ,
b1100 #
b1100 +
b11111001001100000110100111110010 '
b11111001001100000110100111110010 .
b11000 %
b11000 -
1&
#140000
0&
#145000
b1001001101110101001000010010 9
b110 ;
b10 :
b1011110100011100010100010111101 =
b10101 <
b1001001101110101001000010010 2
b110 4
b10 3
b1011110100011100010100010111101 6
b10101 5
b101 *
1&
#150000
0&
#155000
b1001001101110101001000010010 !
b1001001101110101001000010010 /
b110 $
b110 ,
b10 #
b10 +
b1011110100011100010100010111101 '
b1011110100011100010100010111101 .
b10101 %
b10101 -
1&
#160000
0&
#165000
b0 9
b11010 ;
b10010 :
b1000000001110110010001010000000 =
b10000 <
b0 2
b11010 4
b10010 3
b1000000001110110010001010000000 6
b10000 5
b110 *
1&
#170000
0&
#175000
b0 !
b0 /
b11010 $
b11010 ,
b10010 #
b10010 +
b1000000001110110010001010000000 '
b1000000001110110010001010000000 .
b10000 %
b10000 -
1&
#180000
0&
#185000
b101 ;
b0 :
b1001100000111011100000010011 =
b1001 <
b101 4
b0 3
b1001100000111011100000010011 6
b1001 5
b111 *
1&
#190000
0&
#195000
b101 $
b101 ,
b0 #
b0 +
b1001100000111011100000010011 '
b1001100000111011100000010011 .
b1001 %
b1001 -
1&
#200000
0&
#205000
b10001 ;
b1010 :
b1000101110100101000000010 =
b1101 <
1>
b10001 4
b1010 3
b1000101110100101000000010 6
b1101 5
17
b1000 *
1&
#210000
0&
#215000
b10001 $
b10001 ,
b1010 #
b1010 +
b1000101110100101000000010 '
b1000101110100101000000010 .
b1101 %
b1101 -
1(
1&
#220000
0&
#225000
b11 ;
b1100 :
b10000101000010010110010100001010 =
b10010 <
0>
b11 4
b1100 3
b10000101000010010110010100001010 6
b10010 5
07
b1001 *
1&
#230000
0&
#235000
b11 $
b11 ,
b1100 #
b1100 +
b10000101000010010110010100001010 '
b10000101000010010110010100001010 .
b10010 %
b10010 -
0(
1&
#240000
0&
#245000
b1000101110100101000000010 8
b10111 ;
b1101 :
b10100000110001001011001101000001 =
b11000 <
1>
b1000101110100101000000010 1
b10111 4
b1101 3
b10100000110001001011001101000001 6
b11000 5
17
b1010 *
1&
#250000
0&
#255000
b1000101110100101000000010 "
b1000101110100101000000010 0
b10111 $
b10111 ,
b1101 #
b1101 +
b10100000110001001011001101000001 '
b10100000110001001011001101000001 .
b11000 %
b11000 -
1(
1&
#260000
0&
#265000
b0 8
b11010 ;
b11100 :
b11011011000000100110010110110110 =
b11110 <
0>
b0 1
b11010 4
b11100 3
b11011011000000100110010110110110 6
b11110 5
07
b1011 *
1&
#270000
0&
#275000
b0 "
b0 0
b11010 $
b11010 ,
b11100 #
b11100 +
b11011011000000100110010110110110 '
b11011011000000100110010110110110 .
b11110 %
b11110 -
0(
1&
#280000
0&
#285000
b10100000110001001011001101000001 9
b11000 ;
b111 :
b101110101111001101000001011 =
b10010 <
b10100000110001001011001101000001 2
b11000 4
b111 3
b101110101111001101000001011 6
b10010 5
b1100 *
1&
#290000
0&
#295000
b10100000110001001011001101000001 !
b10100000110001001011001101000001 /
b11000 $
b11000 ,
b111 #
b111 +
b101110101111001101000001011 '
b101110101111001101000001011 .
b10010 %
b10010 -
1&
#300000
0&
#305000
b0 9
b10001 ;
b10011101000001100011001100111010 =
b11 <
1>
b0 2
b10001 4
b10011101000001100011001100111010 6
b11 5
17
b1101 *
1&
#310000
0&
#315000
b0 !
b0 /
b10001 $
b10001 ,
b10011101000001100011001100111010 '
b10011101000001100011001100111010 .
b11 %
b11 -
1(
1&
#320000
0&
#325000
b11001 ;
b10100 :
b10110001001000110000011101100010 =
b11101 <
b11001 4
b10100 3
b10110001001000110000011101100010 6
b11101 5
b1110 *
1&
#330000
0&
#335000
b11001 $
b11001 ,
b10100 #
b10100 +
b10110001001000110000011101100010 '
b10110001001000110000011101100010 .
b11101 %
b11101 -
1&
#340000
0&
#345000
b101 ;
b1001 :
b1011011110011010110000010110111 =
b11111 <
b101 4
b1001 3
b1011011110011010110000010110111 6
b11111 5
b1111 *
1&
#350000
0&
#355000
b101 $
b101 ,
b1001 #
b1001 +
b1011011110011010110000010110111 '
b1011011110011010110000010110111 .
b11111 %
b11111 -
1&
#360000
0&
#365000
b1000101110100101000000010 9
b1000101110100101000000010 8
b1101 ;
b1101 :
b100100101011100011001001001001 =
b11000 <
0>
b1000101110100101000000010 2
b1000101110100101000000010 1
b1101 4
b1101 3
b100100101011100011001001001001 6
b11000 5
07
b10000 *
1&
#370000
0&
#375000
b1000101110100101000000010 !
b1000101110100101000000010 /
b1000101110100101000000010 "
b1000101110100101000000010 0
b1101 $
b1101 ,
b1101 #
b1101 +
b100100101011100011001001001001 '
b100100101011100011001001001001 .
b11000 %
b11000 -
0(
1&
#380000
0&
#385000
b0 9
b0 8
b11100 ;
b1100 :
b10000110000111010111111100001100 =
b11001 <
b0 2
b0 1
b11100 4
b1100 3
b10000110000111010111111100001100 6
b11001 5
b10001 *
1&
#390000
0&
#395000
b0 !
b0 /
b0 "
b0 0
b11100 $
b11100 ,
b1100 #
b1100 +
b10000110000111010111111100001100 '
b10000110000111010111111100001100 .
b11001 %
b11001 -
1&
#400000
0&
#405000
b10110 ;
b111 :
b10001001000011001101101100010010 =
b10011 <
b10110 4
b111 3
b10001001000011001101101100010010 6
b10011 5
b10010 *
1&
#410000
0&
#415000
b10110 $
b10110 ,
b111 #
b111 +
b10001001000011001101101100010010 '
b10001001000011001101101100010010 .
b10011 %
b10011 -
1&
#420000
0&
#425000
b10100000110001001011001101000001 8
b111 ;
b11000 :
b1101001111010111111011011010011 =
b10001 <
1>
b10100000110001001011001101000001 1
b111 4
b11000 3
b1101001111010111111011011010011 6
b10001 5
17
b10011 *
1&
#430000
0&
#435000
b10100000110001001011001101000001 "
b10100000110001001011001101000001 0
b111 $
b111 ,
b11000 #
b11000 +
b1101001111010111111011011010011 '
b1101001111010111111011011010011 .
b10001 %
b10001 -
1(
1&
#440000
0&
#445000
b0 8
b10101 ;
b10010 :
b11111111100101010111000111111 =
b10100 <
b0 1
b10101 4
b10010 3
b11111111100101010111000111111 6
b10100 5
b10100 *
1&
#450000
0&
#455000
b0 "
b0 0
b10101 $
b10101 ,
b10010 #
b10010 +
b11111111100101010111000111111 '
b11111111100101010111000111111 .
b10100 %
b10100 -
1&
#460000
0&
#465000
b1011011110011010110000010110111 8
b10 ;
b11111 :
b1001110001011111111001010011100 =
b1000 <
0>
b1011011110011010110000010110111 1
b10 4
b11111 3
b1001110001011111111001010011100 6
b1000 5
07
b10101 *
1&
#470000
0&
#475000
b1011011110011010110000010110111 "
b1011011110011010110000010110111 0
b10 $
b10 ,
b11111 #
b11111 +
b1001110001011111111001010011100 '
b1001110001011111111001010011100 .
b1000 %
b1000 -
0(
1&
#480000
0&
#485000
b0 8
b101 ;
b1011 :
b10111100110011010100000101111 =
b1010 <
1>
b0 1
b101 4
b1011 3
b10111100110011010100000101111 6
b1010 5
17
b10110 *
1&
#490000
0&
#495000
b0 "
b0 0
b101 $
b101 ,
b1011 #
b1011 +
b10111100110011010100000101111 '
b10111100110011010100000101111 .
b1010 %
b1010 -
1(
1&
#500000
0&
#505000
b10101 ;
b1110 :
b1100101100110110011011011001011 =
b11111 <
b10101 4
b1110 3
b1100101100110110011011011001011 6
b11111 5
b10111 *
1&
#510000
0&
#515000
b10101 $
b10101 ,
b1110 #
b1110 +
b1100101100110110011011011001011 '
b1100101100110110011011011001011 .
b11111 %
b11111 -
1&
#520000
0&
#525000
b1001001101110101001000010010 8
b1011 ;
b110 :
b1101101010100110110110011011010 =
b1110 <
b1001001101110101001000010010 1
b1011 4
b110 3
b1101101010100110110110011011010 6
b1110 5
b11000 *
1&
#530000
0&
#535000
b1001001101110101001000010010 "
b1001001101110101001000010010 0
b1011 $
b1011 ,
b110 #
b110 +
b1101101010100110110110011011010 '
b1101101010100110110110011011010 .
b1110 %
b1110 -
1&
#540000
0&
#545000
b1000101110100101000000010 8
b10010 ;
b1101 :
b10100010001100011111111101000100 =
b10111 <
0>
b1000101110100101000000010 1
b10010 4
b1101 3
b10100010001100011111111101000100 6
b10111 5
07
b11001 *
1&
#550000
0&
#555000
b1000101110100101000000010 "
b1000101110100101000000010 0
b10010 $
b10010 ,
b1101 #
b1101 +
b10100010001100011111111101000100 '
b10100010001100011111111101000100 .
b10111 %
b10111 -
0(
1&
#560000
0&
#565000
b0 8
b1111 ;
b1001 :
b11101110010111011010110111011100 =
b10000 <
1>
b0 1
b1111 4
b1001 3
b11101110010111011010110111011100 6
b10000 5
17
b11010 *
1&
#570000
0&
#575000
b0 "
b0 0
b1111 $
b1111 ,
b1001 #
b1001 +
b11101110010111011010110111011100 '
b11101110010111011010110111011100 .
b10000 %
b10000 -
1(
1&
#580000
0&
#585000
b1001001101110101001000010010 8
b0 ;
b110 :
b10100111011110011110100101001110 =
b10101 <
0>
b1001001101110101001000010010 1
b0 4
b110 3
b10100111011110011110100101001110 6
b10101 5
07
b11011 *
1&
#590000
0&
#595000
b1001001101110101001000010010 "
b1001001101110101001000010010 0
b0 $
b0 ,
b110 #
b110 +
b10100111011110011110100101001110 '
b10100111011110011110100101001110 .
b10101 %
b10101 -
0(
1&
#600000
0&
#605000
b0 8
b11001 ;
b1011 :
b10111100110100011000011101111001 =
b11 <
1>
b0 1
b11001 4
b1011 3
b10111100110100011000011101111001 6
b11 5
17
b11100 *
1&
#610000
0&
#615000
b0 "
b0 0
b11001 $
b11001 ,
b1011 #
b1011 +
b10111100110100011000011101111001 '
b10111100110100011000011101111001 .
b11 %
b11 -
1(
1&
#620000
0&
#625000
b10110001001000110000011101100010 8
b100 ;
b11101 :
b101100101101111100101001011001 =
b0 <
b10110001001000110000011101100010 1
b100 4
b11101 3
b101100101101111100101001011001 6
b0 5
b11101 *
1&
#630000
0&
#635000
b10110001001000110000011101100010 "
b10110001001000110000011101100010 0
b100 $
b100 ,
b11101 #
b11101 +
b101100101101111100101001011001 '
b101100101101111100101001011001 .
b0 %
b0 -
1&
#640000
0&
#645000
b0 8
b11011 ;
b11100 :
b111011010001011110001001110110 =
b110 <
b0 1
b11011 4
b11100 3
b111011010001011110001001110110 6
b110 5
b11110 *
1&
#650000
0&
#655000
b0 "
b0 0
b11011 $
b11011 ,
b11100 #
b11100 +
b111011010001011110001001110110 '
b111011010001011110001001110110 .
b110 %
b110 -
1&
#660000
0&
#665000
b1100101100110110011011011001011 8
b10110 ;
b11111 :
b10000010011101001001101100000100 =
b100 <
b1100101100110110011011011001011 1
b10110 4
b11111 3
b10000010011101001001101100000100 6
b100 5
b11111 *
1&
#670000
0&
#675000
b1100101100110110011011011001011 "
b1100101100110110011011011001011 0
b10110 $
b10110 ,
b11111 #
b11111 +
b10000010011101001001101100000100 '
b10000010011101001001101100000100 .
b100 %
b100 -
1&
#680000
0&
#685000
b0 8
b1100 ;
b10 :
b10010100011111001101100100101000 =
b11000 <
0>
b0 1
b1100 4
b10 3
b10010100011111001101100100101000 6
b11000 5
07
b100000 *
1&
#690000
0&
#695000
b0 "
b0 0
b1100 $
b1100 ,
b10 #
b10 +
b10010100011111001101100100101000 '
b10010100011111001101100100101000 .
b11000 %
b11000 -
0(
1&
#700000
0&
#705000
b10010 ;
b1111 :
b10001110010000010100010100011100 =
b0 <
b10010 4
b1111 3
b10001110010000010100010100011100 6
b0 5
b100001 *
1&
#710000
0&
#715000
b10010 $
b10010 ,
b1111 #
b1111 +
b10001110010000010100010100011100 '
b10001110010000010100010100011100 .
b0 %
b0 -
1&
#720000
0&
#725000
b10111100110100011000011101111001 8
b10110 ;
b11 :
b1101101001101000000100011011010 =
b11000 <
b10111100110100011000011101111001 1
b10110 4
b11 3
b1101101001101000000100011011010 6
b11000 5
b100010 *
1&
#730000
0&
#735000
b10111100110100011000011101111001 "
b10111100110100011000011101111001 0
b10110 $
b10110 ,
b11 #
b11 +
b1101101001101000000100011011010 '
b1101101001101000000100011011010 .
b11000 %
b11000 -
1&
#740000
0&
#745000
b1100101100110110011011011001011 9
b0 8
b11111 ;
b10101 :
b11011101011100011001100110111010 =
b111 <
b1100101100110110011011011001011 2
b0 1
b11111 4
b10101 3
b11011101011100011001100110111010 6
b111 5
b100011 *
1&
#750000
0&
#755000
b1100101100110110011011011001011 !
b1100101100110110011011011001011 /
b0 "
b0 0
b11111 $
b11111 ,
b10101 #
b10101 +
b11011101011100011001100110111010 '
b11011101011100011001100110111010 .
b111 %
b111 -
1&
#760000
0&
#765000
b0 9
b11110110110101000101011111101101 8
b11001 ;
b10011 :
b1011100111100000000000010111001 =
b1 <
1>
b0 2
b11110110110101000101011111101101 1
b11001 4
b10011 3
b1011100111100000000000010111001 6
b1 5
17
b100100 *
1&
#770000
0&
#775000
b0 !
b0 /
b11110110110101000101011111101101 "
b11110110110101000101011111101101 0
b11001 $
b11001 ,
b10011 #
b10011 +
b1011100111100000000000010111001 '
b1011100111100000000000010111001 .
b1 %
b1 -
1(
1&
#780000
0&
#785000
b10110001001000110000011101100010 9
b0 8
b11101 ;
b10111 :
b1011011010001100001101010110110 =
b10010 <
b10110001001000110000011101100010 2
b0 1
b11101 4
b10111 3
b1011011010001100001101010110110 6
b10010 5
b100101 *
1&
#790000
0&
#795000
b10110001001000110000011101100010 !
b10110001001000110000011101100010 /
b0 "
b0 0
b11101 $
b11101 ,
b10111 #
b10111 +
b1011011010001100001101010110110 '
b1011011010001100001101010110110 .
b10010 %
b10010 -
1&
#800000
0&
#805000
b0 9
b1000101110100101000000010 8
b1100 ;
b1101 :
b10111111010110101001101101111110 =
b10111 <
b0 2
b1000101110100101000000010 1
b1100 4
b1101 3
b10111111010110101001101101111110 6
b10111 5
b100110 *
1&
#810000
0&
#815000
b0 !
b0 /
b1000101110100101000000010 "
b1000101110100101000000010 0
b1100 $
b1100 ,
b1101 #
b1101 +
b10111111010110101001101101111110 '
b10111111010110101001101101111110 .
b10111 %
b10111 -
1&
#820000
0&
#825000
b10111100110011010100000101111 9
b1101001111010111111011011010011 8
b1010 ;
b10001 :
b110000101111001110111001100001 =
b1111 <
b10111100110011010100000101111 2
b1101001111010111111011011010011 1
b1010 4
b10001 3
b110000101111001110111001100001 6
b1111 5
b100111 *
1&
#830000
0&
#835000
b10111100110011010100000101111 !
b10111100110011010100000101111 /
b1101001111010111111011011010011 "
b1101001111010111111011011010011 0
b1010 $
b1010 ,
b10001 #
b10001 +
b110000101111001110111001100001 '
b110000101111001110111001100001 .
b1111 %
b1111 -
1&
#840000
0&
#845000
b0 9
b10111100110100011000011101111001 8
b10 ;
b11 :
b11111010100011000101100111110101 =
b101 <
b0 2
b10111100110100011000011101111001 1
b10 4
b11 3
b11111010100011000101100111110101 6
b101 5
b101000 *
1&
#850000
0&
#855000
b0 !
b0 /
b10111100110100011000011101111001 "
b10111100110100011000011101111001 0
b10 $
b10 ,
b11 #
b11 +
b11111010100011000101100111110101 '
b11111010100011000101100111110101 .
b101 %
b101 -
1&
#860000
0&
#865000
b11111111100101010111000111111 8
b111 ;
b10100 :
b1001100000000011011010010011000 =
b1100 <
b11111111100101010111000111111 1
b111 4
b10100 3
b1001100000000011011010010011000 6
b1100 5
b101001 *
1&
#870000
0&
#875000
b11111111100101010111000111111 "
b11111111100101010111000111111 0
b111 $
b111 ,
b10100 #
b10100 +
b1001100000000011011010010011000 '
b1001100000000011011010010011000 .
b1100 %
b1100 -
1&
#880000
0&
#885000
b10111100110011010100000101111 8
b11010 ;
b1010 :
b10100111010110001101000101001110 =
b1000 <
0>
b10111100110011010100000101111 1
b11010 4
b1010 3
b10100111010110001101000101001110 6
b1000 5
07
b101010 *
1&
#890000
0&
#895000
b10111100110011010100000101111 "
b10111100110011010100000101111 0
b11010 $
b11010 ,
b1010 #
b1010 +
b10100111010110001101000101001110 '
b10100111010110001101000101001110 .
b1000 %
b1000 -
0(
1&
#900000
0&
#905000
b1011011010001100001101010110110 9
b0 8
b10010 ;
b1001 :
b1110011001101000110011011100110 =
b10000 <
b1011011010001100001101010110110 2
b0 1
b10010 4
b1001 3
b1110011001101000110011011100110 6
b10000 5
b101011 *
1&
#910000
0&
#915000
b1011011010001100001101010110110 !
b1011011010001100001101010110110 /
b0 "
b0 0
b10010 $
b10010 ,
b1001 #
b1001 +
b1110011001101000110011011100110 '
b1110011001101000110011011100110 .
b10000 %
b10000 -
1&
#920000
0&
#925000
b0 9
b10111100110100011000011101111001 8
b111 ;
b11 :
b11001111011101011111111110011110 =
b1000 <
1>
b0 2
b10111100110100011000011101111001 1
b111 4
b11 3
b11001111011101011111111110011110 6
b1000 5
17
b101100 *
1&
#930000
0&
#935000
b0 !
b0 /
b10111100110100011000011101111001 "
b10111100110100011000011101111001 0
b111 $
b111 ,
b11 #
b11 +
b11001111011101011111111110011110 '
b11001111011101011111111110011110 .
b1000 %
b1000 -
1(
1&
#940000
0&
#945000
b1001100000000011011010010011000 9
b0 8
b1100 ;
b10110 :
b10001001111111110100000100010011 =
b11100 <
b1001100000000011011010010011000 2
b0 1
b1100 4
b10110 3
b10001001111111110100000100010011 6
b11100 5
b101101 *
1&
#950000
0&
#955000
b1001100000000011011010010011000 !
b1001100000000011011010010011000 /
b0 "
b0 0
b1100 $
b1100 ,
b10110 #
b10110 +
b10001001111111110100000100010011 '
b10001001111111110100000100010011 .
b11100 %
b11100 -
1&
#960000
0&
#965000
b0 9
b11001 ;
b11011 :
b11100010000101101010101111000100 =
b11011 <
b0 2
b11001 4
b11011 3
b11100010000101101010101111000100 6
b11011 5
b101110 *
1&
#970000
0&
#975000
b0 !
b0 /
b11001 $
b11001 ,
b11011 #
b11011 +
b11100010000101101010101111000100 '
b11100010000101101010101111000100 .
b11011 %
b11011 -
1&
#980000
0&
#985000
b11100010000101101010101111000100 "
b11100010000101101010101111000100 0
b110000101111001110111001100001 9
b1100101100110110011011011001011 8
b1111 ;
b11111 :
b1000011001100111001000010000110 =
b10111 <
0>
b110000101111001110111001100001 2
b1100101100110110011011011001011 1
b1111 4
b11111 3
b1000011001100111001000010000110 6
b10111 5
07
b101111 *
1&
#990000
0&
#995000
b110000101111001110111001100001 !
b110000101111001110111001100001 /
b1100101100110110011011011001011 "
b1100101100110110011011011001011 0
b1111 $
b1111 ,
b11111 #
b11111 +
b1000011001100111001000010000110 '
b1000011001100111001000010000110 .
b10111 %
b10111 -
0(
1&
#1000000
0&
#1005000
b10001001111111110100000100010011 9
b1101101010100110110110011011010 8
b11100 ;
b1110 :
b11000010010011111100110110000100 =
b1011 <
1>
b10001001111111110100000100010011 2
b1101101010100110110110011011010 1
b11100 4
b1110 3
b11000010010011111100110110000100 6
b1011 5
17
b110000 *
1&
#1010000
0&
#1015000
b10001001111111110100000100010011 !
b10001001111111110100000100010011 /
b1101101010100110110110011011010 "
b1101101010100110110110011011010 0
b11100 $
b11100 ,
b1110 #
b1110 +
b11000010010011111100110110000100 '
b11000010010011111100110110000100 .
b1011 %
b1011 -
1(
1&
#1020000
0&
#1025000
b0 9
b110000101111001110111001100001 8
b0 ;
b1111 :
b11000111011001011010100110001110 =
b1010 <
b0 2
b110000101111001110111001100001 1
b0 4
b1111 3
b11000111011001011010100110001110 6
b1010 5
b110001 *
1&
#1030000
0&
#1035000
b0 !
b0 /
b110000101111001110111001100001 "
b110000101111001110111001100001 0
b0 $
b0 ,
b1111 #
b1111 +
b11000111011001011010100110001110 '
b11000111011001011010100110001110 .
b1010 %
b1010 -
1&
#1040000
0&
#1045000
b11001111011101011111111110011110 9
b0 8
b1000 ;
b111 :
b10011011011000001110010100110110 =
b11100 <
0>
b11001111011101011111111110011110 2
b0 1
b1000 4
b111 3
b10011011011000001110010100110110 6
b11100 5
07
b110010 *
1&
#1050000
0&
#1055000
b11001111011101011111111110011110 !
b11001111011101011111111110011110 /
b0 "
b0 0
b1000 $
b1000 ,
b111 #
b111 +
b10011011011000001110010100110110 '
b10011011011000001110010100110110 .
b11100 %
b11100 -
0(
1&
#1060000
0&
#1065000
b0 9
b11001 ;
b11001 :
b1010111001111111011010010101110 =
b11000 <
1>
b0 2
b11001 4
b11001 3
b1010111001111111011010010101110 6
b11000 5
17
b110011 *
1&
#1070000
0&
#1075000
b0 !
b0 /
b11001 $
b11001 ,
b11001 #
b11001 +
b1010111001111111011010010101110 '
b1010111001111111011010010101110 .
b11000 %
b11000 -
1(
1&
#1080000
0&
#1085000
b1011100111100000000000010111001 9
b1001100000000011011010010011000 8
b1 ;
b1100 :
b10100101101101110101111101001011 =
b10 <
b1011100111100000000000010111001 2
b1001100000000011011010010011000 1
b1 4
b1100 3
b10100101101101110101111101001011 6
b10 5
b110100 *
1&
#1090000
0&
#1095000
b1011100111100000000000010111001 !
b1011100111100000000000010111001 /
b1001100000000011011010010011000 "
b1001100000000011011010010011000 0
b1 $
b1 ,
b1100 #
b1100 +
b10100101101101110101111101001011 '
b10100101101101110101111101001011 .
b10 %
b10 -
1&
#1100000
0&
#1105000
b11001111011101011111111110011110 9
b10110001001000110000011101100010 8
b1000 ;
b11101 :
b10001100000000111001110100011000 =
b11110 <
b11001111011101011111111110011110 2
b10110001001000110000011101100010 1
b1000 4
b11101 3
b10001100000000111001110100011000 6
b11110 5
b110101 *
1&
#1110000
0&
