files/alu.sv
/*
Alu module for RISC-V 32-bit single-cycle processor.

base on alu decoder truth table from documentation.

outputs:
result : 32-bit result of the ALU operation
zero : 1-bit flag that is set to 1 if the result is zero, otherwise 0

*/

module alu (
    
    //inputs
    input logic [31:0] a, 
    input logic [31:0] b,
    input logic [3:0] ALUControl,

    //outputs
    output logic [31:0] y,
    output logic Zero,
    output logic Neg,
    output logic NegU
);



    //if ALUControl[0] is 1, we want to perform subtraction, which is equivalent to adding the
    // two's complement of b (i.e., ~b + 1)
    // if ALUControl[0] is 0, we want to perform addition, which is just a + b


    wire [31:0] b_eff   = b ^ {32{ALUControl[0]}};   // B or ~B
    wire        cin     = ALUControl[0];             // 0: ADD, 1: SUB

    // wide adders so we get carries
    wire [32:0] sum_agg  = {1'b0, a} + {1'b0, b_eff} + cin;     // full 32b add
    wire [31:0] sum     = sum_agg[31:0];
    wire        c_out   = sum_agg[32];

    // carry *into* MSB (from lower 31 bits) for signed overflow detection
    wire [31:0] low_sum31;
    wire        c_in31;
    assign {c_in31, low_sum31[30:0]} =
        {1'b0, a[30:0]} + {1'b0, b_eff[30:0]} + cin;

    // Flags
    wire N = sum[31];
    wire V = c_in31 ^ c_out;     // signed overflow (add/sub)
    wire C = c_out;              // carry-out (for unsigned)
            

    assign Zero = (y == 32'b0);
    assign Neg  = N ^ V;         // a < b (signed)  from a-b path
    assign NegU = ~C;            // a < b (unsigned) : borrow = ~carry

    logic [4:0] shamt;
    assign shamt = b[4:0]; //logical shamt is rs2[4:0] or uimm = immediate[4:0] for shift instructions

    always_comb begin
        case (ALUControl)
            4'b0000: y = sum;                                  // add
            4'b0001: y = sum;                                  // SUB
            4'b0010: y = $unsigned(a) << shamt;                // slli ,sll
            4'b0011: y = Neg;                                  // slti , slt (using sub method as before)
            4'b1011: y = NegU   ;                               // sltu, sltiu
            4'b0100: y = a ^ b;                                 // xori .xor
            4'b0101: y = $unsigned(a) >> shamt;                 // srli, srl            
            4'b1101: y = $signed(a) >>> shamt;                  // srai, sra
            4'b0110: y = a | b;                                 // ori, or
            4'b0111: y = a & b;                                 // andi, and   

            default: y = 32'bxxxx_xxxx_xxxx_xxxx_xxxx_xxxx_xxxx_xxxx; // undefined
        endcase
    end

    

endmodule

tb/alu_tb.sv
`timescale 1ns/1ps

module tb_top;
    // Signals
    logic clk;
    logic [31:0] a, b;
    logic [3:0]  ALUControl;
    logic [31:0] y;
    logic        Zero, Neg, NegU;

    // 1. Clock Generation
    always #5 clk = (clk === 1'b0); 

    // 2. DUT Instantiation
    alu dut (
        .a(a),
        .b(b),
        .ALUControl(ALUControl),
        .y(y),
        .Zero(Zero),
        .Neg(Neg),
        .NegU(NegU)
    );

    // 3. Driver Task (Acts as the "Driver")
    task drive(input [31:0] ta, input [31:0] tb, input [3:0] top);
        @(posedge clk);
        a <= ta;
        b <= tb;
        ALUControl <= top;
    endtask

    // 4. Monitor & Scoreboard Logic (Check results)
    always @(posedge clk) begin
        #1; // Wait for combinational logic to settle
        $display("Time:%0t | OP:%b | A:%h B:%h | Y:%h Zero:%b", 
                 $time, ALUControl, a, b, y, Zero);
        
        // Simple Scoreboard Check for ADD
        if (ALUControl == 4'b0000 && (y !== a + b)) 
            $error("ADD FAILED!");
    end

    // 5. Generator (The main test sequence)
    initial begin
        // Initialize VCD dumping
        $dumpfile("sim/alu_trace.vcd");
        $dumpvars(0, tb_top);

        // Initialize signals
        clk = 0;
        a = 0; b = 0; ALUControl = 0;

        $display("--- Starting Tests ---");

        // Test ADD
        drive(32'd10, 32'd5, 4'b0000);
        assert (y == (a + b)) 
    else $error("Addition failed! Expected %d, got %d", (a + b), y);

        
        // Test SUB
        drive(32'd20, 32'd8, 4'b0001);

        // Test Random cases (Icarus supports $urandom)
        repeat(5) begin
            drive($urandom, $urandom, 4'b0000); // Test 5 random ADDs
        end

        #20;
        $display("--- Tests Finished ---");
        $finish;
    end

endmodule

sim/alu_trace.vcd
$date
	Wed May 13 18:48:22 2026
$end
$version
	Icarus Verilog
$end
$timescale
	1ps
$end
$scope module tb_top $end
$var wire 32 ! y [31:0] $end
$var wire 1 " Zero $end
$var wire 1 # NegU $end
$var wire 1 $ Neg $end
$var reg 4 % ALUControl [3:0] $end
$var reg 32 & a [31:0] $end
$var reg 32 ' b [31:0] $end
$var reg 1 ( clk $end
$scope module dut $end
$var wire 4 ) ALUControl [3:0] $end
$var wire 1 * C $end
$var wire 1 $ Neg $end
$var wire 1 # NegU $end
$var wire 1 + V $end
$var wire 32 , a [31:0] $end
$var wire 32 - b [31:0] $end
$var wire 32 . b_eff [31:0] $end
$var wire 33 / sum_agg [32:0] $end
$var wire 32 0 sum [31:0] $end
$var wire 5 1 shamt [4:0] $end
$var wire 32 2 low_sum31 [31:0] $end
$var wire 1 3 cin $end
$var wire 1 4 c_out $end
$var wire 1 5 c_in31 $end
$var wire 1 " Zero $end
$var wire 1 6 N $end
$var reg 32 7 y [31:0] $end
$upscope $end
$scope task drive $end
$var reg 32 8 ta [31:0] $end
$var reg 32 9 tb [31:0] $end
$var reg 4 : top [3:0] $end
$upscope $end
$upscope $end
$enddefinitions $end
$comment Show the parameter values. $end
$dumpall
$end
#0
$dumpvars
b0 :
b101 9
b1010 8
b0 7
06
05
04
03
bz0000000000000000000000000000000 2
b0 1
b0 0
b0 /
b0 .
b0 -
b0 ,
0+
0*
b0 )
0(
b0 '
b0 &
b0 %
0$
1#
1"
b0 !
$end
#5000
bz0000000000000000000000000001111 2
b101 .
b101 1
0"
b1111 !
b1111 7
b1111 0
b101 '
b101 -
b1111 /
b1010 &
b1010 ,
b1 :
b1000 9
b10100 8
1(
#10000
0(
#15000
0#
15
1*
14
bz0000000000000000000000000001100 2
13
b11111111111111111111111111110111 .
b1000 1
b1100 !
b1100 7
b1100 0
b1 %
b1 )
b1000 '
b1000 -
b100000000000000000000000000001100 /
b10100 &
b10100 ,
b0 :
b1000000100010010101111010000001 9
b10010010000101010011010100100100 8
1(
#20000
0(
#25000
1#
0*
04
05
1$
16
bz1010010100111101001001110100101 2
03
b1000000100010010101111010000001 .
b1 1
b11010010100111101001001110100101 !
b11010010100111101001001110100101 7
b11010010100111101001001110100101 0
b0 %
b0 )
b1000000100010010101111010000001 '
b1000000100010010101111010000001 -
b11010010100111101001001110100101 /
b10010010000101010011010100100100 &
b10010010000101010011010100100100 ,
b110001111100000101011001100011 9
b100100001001101011000001001 8
1(
#30000
0(
#35000
0$
06
bz0110110011101010010110001101100 2
b110001111100000101011001100011 .
b11 1
b110110011101010010110001101100 !
b110110011101010010110001101100 7
b110110011101010010110001101100 0
b110001111100000101011001100011 '
b110001111100000101011001100011 -
b110110011101010010110001101100 /
b100100001001101011000001001 &
b100100001001101011000001001 ,
b11000110110111111001100110001101 9
b10000110101110010111101100001101 8
1(
#40000
0(
#45000
0#
1+
1$
1*
14
06
bz1001101100110010001010010011010 2
b11000110110111111001100110001101 .
b1101 1
b1001101100110010001010010011010 !
b1001101100110010001010010011010 7
b1001101100110010001010010011010 0
b11000110110111111001100110001101 '
b11000110110111111001100110001101 -
b101001101100110010001010010011010 /
b10000110101110010111101100001101 &
b10000110101110010111101100001101 ,
b1001001101110101001000010010 9
b110010110000101000010001100101 8
1(
#50000
0(
#55000
0$
06
1#
0+
bz0111011111110011101011001110111 2
b1001001101110101001000010010 .
b10010 1
b111011111110011101011001110111 !
b111011111110011101011001110111 7
b111011111110011101011001110111 0
0*
04
b1001001101110101001000010010 '
b1001001101110101001000010010 -
b111011111110011101011001110111 /
b110010110000101000010001100101 &
b110010110000101000010001100101 ,
b10000110110101111100110100001101 9
b10000000111100111110001100000001 8
1(
#60000
0(
#65000
0#
1+
1$
1*
14
06
bz0000111110010111011000000001110 2
b10000110110101111100110100001101 .
b1101 1
b111110010111011000000001110 !
b111110010111011000000001110 7
b111110010111011000000001110 0
b10000110110101111100110100001101 '
b10000110110101111100110100001101 -
b100000111110010111011000000001110 /
b10000000111100111110001100000001 &
b10000000111100111110001100000001 ,
1(
